ittapi-1.2.0.dist-info/GPL-2.0-only.txt
ittapi-1.2.0.dist-info/METADATA
ittapi-1.2.0.dist-info/top_level.txt
ittapi-1.2.0.dist-info/RECORD
ittapi-1.2.0.dist-info/WHEEL
ittapi-1.2.0.dist-info/BSD-3-Clause.txt
ittapi/collection_control.py
ittapi/task.py
ittapi/thread_naming.py
ittapi/__init__.py
ittapi/string_handle.py
ittapi/pt_region.py
ittapi/native.cpython-39-x86_64-linux-gnu.so
ittapi/id.py
ittapi/event.py
ittapi/region.py
ittapi/domain.py
ittapi/compat/task.py
ittapi/compat/__init__.py
ittapi/compat/pt_region.py
