Metadata-Version: 2.1
Name: ittapi
Version: 1.2.0
Summary: Python bindings to Intel Instrumentation and Tracing Technology (ITT) API.
Author: Egor Suldin
Project-URL: Homepage, https://github.com/intel/ittapi
Project-URL: Bug Tracker, https://github.com/intel/ittapi/issues
Classifier: License :: OSI Approved :: BSD License
Classifier: Operating System :: Microsoft :: Windows
Classifier: Operating System :: POSIX :: Linux
Classifier: Programming Language :: Python :: 3.8
Classifier: Programming Language :: Python :: 3.9
Classifier: Programming Language :: Python :: 3.10
Classifier: Programming Language :: Python :: 3.11
Classifier: Programming Language :: Python :: 3.12
Requires-Python: >=3.8
License-File: ../LICENSES/BSD-3-Clause.txt
License-File: ../LICENSES/GPL-2.0-only.txt
